merchantsapi/__init__.py
merchantsapi/fixtures.py
merchantsapi/features/__init__.py
merchantsapi/features/test_steps.py
merchantsapi/models/__init__.py
merchantsapi/models/merchants_api.py
merchantsapi/steps/__init__.py
merchantsapi/steps/merchants_api_steps.py
merchantsapi-0.0.1.dist-info/METADATA
merchantsapi-0.0.1.dist-info/WHEEL
merchantsapi-0.0.1.dist-info/top_level.txt
merchantsapi-0.0.1.dist-info/RECORD
