Metadata-Version: 2.1
Name: merchantsapi
Version: 0.0.1
Summary: Merchants api test code
Author-email: RR <richard.rawson@divido.com>
Classifier: Programming Language :: Python :: 3
Classifier: Operating System :: OS Independent
Requires-Python: >=3.7
Requires-Dist: deepdiff
Requires-Dist: playwright
Requires-Dist: pytest
